[{"id": 19170098, "url": "https://fr.vestiairecollective.com//women-clothing/tops/jean-paul-gaultier/white-cotton-jean-paul-gaultier-top-19170098.shtml", "brand": "jean-paul-gaultier", "page_no": 0, "description": "<ul _ngcontent-vc-app-c187=\"\" class=\"descriptionList__block__list descriptionList__block__list--detail\"><li _ngcontent-vc-app-c187=\"\">Online since:<!-- --> 11/11/2021 </li><li _ngcontent-vc-app-c187=\"\">Categories : <!-- --> Women </li><li _ngcontent-vc-app-c187=\"\">Category:<!-- --> Clothing </li><li _ngcontent-vc-app-c187=\"\">Sub-category:<!-- --> Tops </li><!-- --><li _ngcontent-vc-app-c187=\"\">Designer:<!-- --> Jean Paul Gaultier </li><!-- --><li _ngcontent-vc-app-c187=\"\"><span _ngcontent-vc-app-c187=\"\">Condition:<!-- --> Very good condition</span><button _ngcontent-vc-app-c187=\"\" class=\"descriptionList__block__list__moreInfo vc-link vc-text-m\">More info</button></li><li _ngcontent-vc-app-c187=\"\">Material:<!-- --> Cotton <!-- --><!-- --><!-- --><!-- --></li><!-- --><!-- --><li _ngcontent-vc-app-c187=\"\">Color:<!-- --> White </li><!-- --><!-- --><li _ngcontent-vc-app-c187=\"\">Size:<!-- --> M International <button _ngcontent-vc-app-c187=\"\" class=\"productDetails__moreInfoLink vc-link vc-text-m\">sizing guide</button><!-- --></li><!-- --><li _ngcontent-vc-app-c187=\"\">Style:<!-- -->Vintage<!-- --></li><!-- --><li _ngcontent-vc-app-c187=\"\">Location:<!-- -->France,\n          from\n          the seller Jack <!-- --><!-- --></li><!-- --><li _ngcontent-vc-app-c187=\"\">Reference:<!-- --> 19170098</li></ul>"}, {"id": 19194430, "url": "https://fr.vestiairecollective.com//women-clothing/skirts/jean-paul-gaultier/multicolour-cotton-elasthane-jean-paul-gaultier-skirt-19194430.shtml", "brand": "jean-paul-gaultier", "page_no": 0, "description": "<ul _ngcontent-vc-app-c187=\"\" class=\"descriptionList__block__list descriptionList__block__list--detail\"><li _ngcontent-vc-app-c187=\"\">Online since:<!-- --> 12/11/2021 </li><li _ngcontent-vc-app-c187=\"\">Categories : <!-- --> Women </li><li _ngcontent-vc-app-c187=\"\">Category:<!-- --> Clothing </li><li _ngcontent-vc-app-c187=\"\">Sub-category:<!-- --> Skirts </li><!-- --><li _ngcontent-vc-app-c187=\"\">Designer:<!-- --> Jean Paul Gaultier </li><!-- --><li _ngcontent-vc-app-c187=\"\"><span _ngcontent-vc-app-c187=\"\">Condition:<!-- --> Very good condition</span><button _ngcontent-vc-app-c187=\"\" class=\"descriptionList__block__list__moreInfo vc-link vc-text-m\">More info</button></li><li _ngcontent-vc-app-c187=\"\">Material:<!-- --> Cotton - elasthane <!-- --><!-- --><!-- --><!-- --></li><!-- --><!-- --><li _ngcontent-vc-app-c187=\"\">Color:<!-- --> Multicolour </li><!-- --><!-- --><li _ngcontent-vc-app-c187=\"\">Size:<!-- --> 38 FR <button _ngcontent-vc-app-c187=\"\" class=\"productDetails__moreInfoLink vc-link vc-text-m\">sizing guide</button><!-- --></li><!-- --><!-- --><li _ngcontent-vc-app-c187=\"\">Location:<!-- -->France,\n          from\n          the seller cassandra<!-- --><!-- --></li><!-- --><li _ngcontent-vc-app-c187=\"\">Reference:<!-- --> 19194430</li></ul>"}, {"id": 19059690, "url": "https://fr.vestiairecollective.com//women-clothing/tops/jean-paul-gaultier/orange-synthetic-jean-paul-gaultier-top-19059690.shtml", "brand": "jean-paul-gaultier", "page_no": 0, "description": "<ul _ngcontent-vc-app-c187=\"\" class=\"descriptionList__block__list descriptionList__block__list--detail\"><li _ngcontent-vc-app-c187=\"\">Online since:<!-- --> 06/11/2021 </li><li _ngcontent-vc-app-c187=\"\">Categories : <!-- --> Women </li><li _ngcontent-vc-app-c187=\"\">Category:<!-- --> Clothing </li><li _ngcontent-vc-app-c187=\"\">Sub-category:<!-- --> Tops </li><!-- --><li _ngcontent-vc-app-c187=\"\">Designer:<!-- --> Jean Paul Gaultier </li><!-- --><li _ngcontent-vc-app-c187=\"\"><span _ngcontent-vc-app-c187=\"\">Condition:<!-- --> Very good condition</span><button _ngcontent-vc-app-c187=\"\" class=\"descriptionList__block__list__moreInfo vc-link vc-text-m\">More info</button></li><li _ngcontent-vc-app-c187=\"\">Material:<!-- --> Synthetic <!-- --><!-- --><!-- --><!-- --></li><!-- --><!-- --><li _ngcontent-vc-app-c187=\"\">Color:<!-- --> Orange </li><!-- --><!-- --><li _ngcontent-vc-app-c187=\"\">Size:<!-- --> 36 FR <button _ngcontent-vc-app-c187=\"\" class=\"productDetails__moreInfoLink vc-link vc-text-m\">sizing guide</button><!-- --></li><!-- --><li _ngcontent-vc-app-c187=\"\">Style:<!-- -->Vintage<!-- --></li><!-- --><li _ngcontent-vc-app-c187=\"\">Location:<!-- -->Belgium,\n          from\n          the seller Fabienne<!-- --><!-- --></li><!-- --><li _ngcontent-vc-app-c187=\"\">Reference:<!-- --> 19059690</li></ul>"}, {"id": 19129509, "url": "https://fr.vestiairecollective.com//women-clothing/tops/jean-paul-gaultier/multicolour-synthetic-jean-paul-gaultier-top-19129509.shtml", "brand": "jean-paul-gaultier", "page_no": 0, "description": "<ul _ngcontent-vc-app-c187=\"\" class=\"descriptionList__block__list descriptionList__block__list--detail\"><li _ngcontent-vc-app-c187=\"\">Online since:<!-- --> 09/11/2021 </li><li _ngcontent-vc-app-c187=\"\">Categories : <!-- --> Women </li><li _ngcontent-vc-app-c187=\"\">Category:<!-- --> Clothing </li><li _ngcontent-vc-app-c187=\"\">Sub-category:<!-- --> Tops </li><!-- --><li _ngcontent-vc-app-c187=\"\">Designer:<!-- --> Jean Paul Gaultier </li><!-- --><li _ngcontent-vc-app-c187=\"\"><span _ngcontent-vc-app-c187=\"\">Condition:<!-- --> Very good condition</span><button _ngcontent-vc-app-c187=\"\" class=\"descriptionList__block__list__moreInfo vc-link vc-text-m\">More info</button></li><li _ngcontent-vc-app-c187=\"\">Material:<!-- --> Synthetic <!-- --><!-- --><!-- --><!-- --></li><!-- --><!-- --><li _ngcontent-vc-app-c187=\"\">Color:<!-- --> Multicolour </li><!-- --><!-- --><li _ngcontent-vc-app-c187=\"\">Size:<!-- --> M International <button _ngcontent-vc-app-c187=\"\" class=\"productDetails__moreInfoLink vc-link vc-text-m\">sizing guide</button><!-- --></li><!-- --><li _ngcontent-vc-app-c187=\"\">Style:<!-- -->Vintage<!-- --></li><!-- --><li _ngcontent-vc-app-c187=\"\">Location:<!-- -->Poland,\n          from\n          the seller adam<!-- --><!-- --></li><!-- --><li _ngcontent-vc-app-c187=\"\">Reference:<!-- --> 19129509</li></ul>"}, {"id": 19143461, "url": "https://fr.vestiairecollective.com//women-clothing/tops/jean-paul-gaultier/multicolour-polyester-jean-paul-gaultier-top-19143461.shtml", "brand": "jean-paul-gaultier", "page_no": 0, "description": "<ul _ngcontent-vc-app-c187=\"\" class=\"descriptionList__block__list descriptionList__block__list--detail\"><li _ngcontent-vc-app-c187=\"\">Online since:<!-- --> 10/11/2021 </li><li _ngcontent-vc-app-c187=\"\">Categories : <!-- --> Women </li><li _ngcontent-vc-app-c187=\"\">Category:<!-- --> Clothing </li><li _ngcontent-vc-app-c187=\"\">Sub-category:<!-- --> Tops </li><!-- --><li _ngcontent-vc-app-c187=\"\">Designer:<!-- --> Jean Paul Gaultier </li><!-- --><li _ngcontent-vc-app-c187=\"\"><span _ngcontent-vc-app-c187=\"\">Condition:<!-- --> Very good condition</span><button _ngcontent-vc-app-c187=\"\" class=\"descriptionList__block__list__moreInfo vc-link vc-text-m\">More info</button></li><li _ngcontent-vc-app-c187=\"\">Material:<!-- --> Polyester <!-- --><!-- --><!-- --><!-- --></li><!-- --><!-- --><li _ngcontent-vc-app-c187=\"\">Color:<!-- --> Multicolour </li><!-- --><!-- --><li _ngcontent-vc-app-c187=\"\">Size:<!-- --> M International <button _ngcontent-vc-app-c187=\"\" class=\"productDetails__moreInfoLink vc-link vc-text-m\">sizing guide</button><!-- --></li><!-- --><li _ngcontent-vc-app-c187=\"\">Style:<!-- -->Vintage<!-- --></li><!-- --><li _ngcontent-vc-app-c187=\"\">Location:<!-- -->Romania,\n          from\n          the seller Andrei<!-- --><!-- --></li><!-- --><li _ngcontent-vc-app-c187=\"\">Reference:<!-- --> 19143461</li></ul>"}, {"id": 19208482, "url": "https://fr.vestiairecollective.com//women-clothing/knitwear/jean-paul-gaultier/multicolour-silk-jean-paul-gaultier-knitwear-19208482.shtml", "brand": "jean-paul-gaultier", "page_no": 0, "description": "<ul _ngcontent-vc-app-c187=\"\" class=\"descriptionList__block__list descriptionList__block__list--detail\"><li _ngcontent-vc-app-c187=\"\">Online since:<!-- --> 13/11/2021 </li><li _ngcontent-vc-app-c187=\"\">Categories : <!-- --> Women </li><li _ngcontent-vc-app-c187=\"\">Category:<!-- --> Clothing </li><li _ngcontent-vc-app-c187=\"\">Sub-category:<!-- --> Knitwear </li><!-- --><li _ngcontent-vc-app-c187=\"\">Designer:<!-- --> Jean Paul Gaultier </li><!-- --><li _ngcontent-vc-app-c187=\"\"><span _ngcontent-vc-app-c187=\"\">Condition:<!-- --> Never worn</span><button _ngcontent-vc-app-c187=\"\" class=\"descriptionList__block__list__moreInfo vc-link vc-text-m\">More info</button></li><li _ngcontent-vc-app-c187=\"\">Material:<!-- --> Silk <!-- --><!-- --><!-- --><!-- --></li><!-- --><!-- --><li _ngcontent-vc-app-c187=\"\">Color:<!-- --> Multicolour </li><!-- --><!-- --><li _ngcontent-vc-app-c187=\"\">Size:<!-- --> 42 FR <button _ngcontent-vc-app-c187=\"\" class=\"productDetails__moreInfoLink vc-link vc-text-m\">sizing guide</button><!-- --></li><!-- --><!-- --><li _ngcontent-vc-app-c187=\"\">Location:<!-- -->Italy,\n          from\n          the seller vanessa<!-- --><!-- --></li><!-- --><li _ngcontent-vc-app-c187=\"\">Reference:<!-- --> 19208482</li></ul>"}, {"id": 19167595, "url": "https://fr.vestiairecollective.com//men-bags/bags/jean-paul-gaultier/beige-cotton-jean-paul-gaultier-bag-19167595.shtml", "brand": "jean-paul-gaultier", "page_no": 0, "description": "<ul _ngcontent-vc-app-c187=\"\" class=\"descriptionList__block__list descriptionList__block__list--detail\"><li _ngcontent-vc-app-c187=\"\">Online since:<!-- --> 11/11/2021 </li><li _ngcontent-vc-app-c187=\"\">Categories : <!-- --> Men </li><li _ngcontent-vc-app-c187=\"\">Category:<!-- --> Bags </li><li _ngcontent-vc-app-c187=\"\">Sub-category:<!-- --> Bags </li><!-- --><li _ngcontent-vc-app-c187=\"\">Designer:<!-- --> Jean Paul Gaultier </li><!-- --><li _ngcontent-vc-app-c187=\"\"><span _ngcontent-vc-app-c187=\"\">Condition:<!-- --> Never worn</span><button _ngcontent-vc-app-c187=\"\" class=\"descriptionList__block__list__moreInfo vc-link vc-text-m\">More info</button></li><li _ngcontent-vc-app-c187=\"\">Material:<!-- --> Cotton <!-- --><!-- --><!-- --><!-- --></li><!-- --><!-- --><li _ngcontent-vc-app-c187=\"\">Color:<!-- --> Beige </li><!-- --><!-- --><!-- --><!-- --><li _ngcontent-vc-app-c187=\"\">Location:<!-- -->United Kingdom,\n          from\n          the seller Rose<!-- --><!-- --></li><!-- --><li _ngcontent-vc-app-c187=\"\">Reference:<!-- --> 19167595</li></ul>"}, {"id": 19182530, "url": "https://fr.vestiairecollective.com//women-clothing/jackets/jean-paul-gaultier/black-wool-jean-paul-gaultier-jacket-19182530.shtml", "brand": "jean-paul-gaultier", "page_no": 0, "description": "<ul _ngcontent-vc-app-c187=\"\" class=\"descriptionList__block__list descriptionList__block__list--detail\"><li _ngcontent-vc-app-c187=\"\">Online since:<!-- --> 12/11/2021 </li><li _ngcontent-vc-app-c187=\"\">Categories : <!-- --> Women </li><li _ngcontent-vc-app-c187=\"\">Category:<!-- --> Clothing </li><li _ngcontent-vc-app-c187=\"\">Sub-category:<!-- --> Jackets </li><!-- --><li _ngcontent-vc-app-c187=\"\">Designer:<!-- --> Jean Paul Gaultier </li><!-- --><li _ngcontent-vc-app-c187=\"\"><span _ngcontent-vc-app-c187=\"\">Condition:<!-- --> Very good condition</span><button _ngcontent-vc-app-c187=\"\" class=\"descriptionList__block__list__moreInfo vc-link vc-text-m\">More info</button></li><li _ngcontent-vc-app-c187=\"\">Material:<!-- --> Wool <!-- --><!-- --><!-- --><!-- --></li><!-- --><!-- --><li _ngcontent-vc-app-c187=\"\">Color:<!-- --> Black </li><!-- --><!-- --><li _ngcontent-vc-app-c187=\"\">Size:<!-- --> 40 FR <button _ngcontent-vc-app-c187=\"\" class=\"productDetails__moreInfoLink vc-link vc-text-m\">sizing guide</button><!-- --></li><!-- --><!-- --><li _ngcontent-vc-app-c187=\"\">Location:<!-- -->Belgium,\n          from\n          the seller alexandra<!-- --><!-- --></li><!-- --><li _ngcontent-vc-app-c187=\"\">Reference:<!-- --> 19182530</li></ul>"}, {"id": 19189796, "url": "https://fr.vestiairecollective.com//women-clothing/jackets/jean-paul-gaultier/black-cotton-jean-paul-gaultier-jacket-19189796.shtml", "brand": "jean-paul-gaultier", "page_no": 0, "description": "<ul _ngcontent-vc-app-c187=\"\" class=\"descriptionList__block__list descriptionList__block__list--detail\"><li _ngcontent-vc-app-c187=\"\">Online since:<!-- --> 12/11/2021 </li><li _ngcontent-vc-app-c187=\"\">Categories : <!-- --> Women </li><li _ngcontent-vc-app-c187=\"\">Category:<!-- --> Clothing </li><li _ngcontent-vc-app-c187=\"\">Sub-category:<!-- --> Jackets </li><!-- --><li _ngcontent-vc-app-c187=\"\">Designer:<!-- --> Jean Paul Gaultier </li><!-- --><li _ngcontent-vc-app-c187=\"\"><span _ngcontent-vc-app-c187=\"\">Condition:<!-- --> Very good condition</span><button _ngcontent-vc-app-c187=\"\" class=\"descriptionList__block__list__moreInfo vc-link vc-text-m\">More info</button></li><li _ngcontent-vc-app-c187=\"\">Material:<!-- --> Cotton <!-- --><!-- --><!-- --><!-- --></li><!-- --><!-- --><li _ngcontent-vc-app-c187=\"\">Color:<!-- --> Black </li><!-- --><!-- --><li _ngcontent-vc-app-c187=\"\">Size:<!-- --> M International <button _ngcontent-vc-app-c187=\"\" class=\"productDetails__moreInfoLink vc-link vc-text-m\">sizing guide</button><!-- --></li><!-- --><li _ngcontent-vc-app-c187=\"\">Style:<!-- -->Vintage<!-- --></li><!-- --><li _ngcontent-vc-app-c187=\"\">Location:<!-- -->France,\n          from\n          the seller Jack <!-- --><!-- --></li><!-- --><li _ngcontent-vc-app-c187=\"\">Reference:<!-- --> 19189796</li></ul>"}, {"id": 19167282, "url": "https://fr.vestiairecollective.com//men-clothing/jeans/jean-paul-gaultier/blue-cotton-elasthane-jean-paul-gaultier-jeans-19167282.shtml", "brand": "jean-paul-gaultier", "page_no": 0, "description": "<ul _ngcontent-vc-app-c187=\"\" class=\"descriptionList__block__list descriptionList__block__list--detail\"><li _ngcontent-vc-app-c187=\"\">Online since:<!-- --> 11/11/2021 </li><li _ngcontent-vc-app-c187=\"\">Categories : <!-- --> Men </li><li _ngcontent-vc-app-c187=\"\">Category:<!-- --> Clothing </li><li _ngcontent-vc-app-c187=\"\">Sub-category:<!-- --> Jeans </li><!-- --><li _ngcontent-vc-app-c187=\"\">Designer:<!-- --> Jean Paul Gaultier </li><!-- --><li _ngcontent-vc-app-c187=\"\"><span _ngcontent-vc-app-c187=\"\">Condition:<!-- --> Very good condition</span><button _ngcontent-vc-app-c187=\"\" class=\"descriptionList__block__list__moreInfo vc-link vc-text-m\">More info</button></li><li _ngcontent-vc-app-c187=\"\">Material:<!-- --> Cotton - elasthane <!-- --><!-- --><!-- --><!-- --></li><!-- --><!-- --><li _ngcontent-vc-app-c187=\"\">Color:<!-- --> Blue </li><!-- --><!-- --><li _ngcontent-vc-app-c187=\"\">Size:<!-- --> 32 US <button _ngcontent-vc-app-c187=\"\" class=\"productDetails__moreInfoLink vc-link vc-text-m\">sizing guide</button><!-- --></li><!-- --><!-- --><li _ngcontent-vc-app-c187=\"\">Location:<!-- -->Italy,\n          from\n          the seller Matteo<!-- --><!-- --></li><!-- --><li _ngcontent-vc-app-c187=\"\">Reference:<!-- --> 19167282</li></ul>"}, {"id": 19163497, "url": "https://fr.vestiairecollective.com//women-clothing/tops/jean-paul-gaultier/black-polyester-jean-paul-gaultier-top-19163497.shtml", "brand": "jean-paul-gaultier", "page_no": 0, "description": "<ul _ngcontent-vc-app-c187=\"\" class=\"descriptionList__block__list descriptionList__block__list--detail\"><li _ngcontent-vc-app-c187=\"\">Online since:<!-- --> 11/11/2021 </li><li _ngcontent-vc-app-c187=\"\">Categories : <!-- --> Women </li><li _ngcontent-vc-app-c187=\"\">Category:<!-- --> Clothing </li><li _ngcontent-vc-app-c187=\"\">Sub-category:<!-- --> Tops </li><!-- --><li _ngcontent-vc-app-c187=\"\">Designer:<!-- --> Jean Paul Gaultier </li><!-- --><li _ngcontent-vc-app-c187=\"\"><span _ngcontent-vc-app-c187=\"\">Condition:<!-- --> Very good condition</span><button _ngcontent-vc-app-c187=\"\" class=\"descriptionList__block__list__moreInfo vc-link vc-text-m\">More info</button></li><li _ngcontent-vc-app-c187=\"\">Material:<!-- --> Polyester <!-- --><!-- --><!-- --><!-- --></li><!-- --><!-- --><li _ngcontent-vc-app-c187=\"\">Color:<!-- --> Black </li><!-- --><!-- --><li _ngcontent-vc-app-c187=\"\">Size:<!-- --> 38 FR <button _ngcontent-vc-app-c187=\"\" class=\"productDetails__moreInfoLink vc-link vc-text-m\">sizing guide</button><!-- --></li><!-- --><!-- --><li _ngcontent-vc-app-c187=\"\">Location:<!-- -->France,\n          from\n          the seller Not<!-- --><!-- --></li><!-- --><li _ngcontent-vc-app-c187=\"\">Reference:<!-- --> 19163497</li></ul>"}, {"id": 19164267, "url": "https://fr.vestiairecollective.com//women-clothing/tops/jean-paul-gaultier/burgundy-polyester-jean-paul-gaultier-top-19164267.shtml", "brand": "jean-paul-gaultier", "page_no": 0, "description": "<ul _ngcontent-vc-app-c187=\"\" class=\"descriptionList__block__list descriptionList__block__list--detail\"><li _ngcontent-vc-app-c187=\"\">Online since:<!-- --> 11/11/2021 </li><li _ngcontent-vc-app-c187=\"\">Categories : <!-- --> Women </li><li _ngcontent-vc-app-c187=\"\">Category:<!-- --> Clothing </li><li _ngcontent-vc-app-c187=\"\">Sub-category:<!-- --> Tops </li><!-- --><li _ngcontent-vc-app-c187=\"\">Designer:<!-- --> Jean Paul Gaultier </li><!-- --><li _ngcontent-vc-app-c187=\"\"><span _ngcontent-vc-app-c187=\"\">Condition:<!-- --> Very good condition</span><button _ngcontent-vc-app-c187=\"\" class=\"descriptionList__block__list__moreInfo vc-link vc-text-m\">More info</button></li><li _ngcontent-vc-app-c187=\"\">Material:<!-- --> Polyester <!-- --><!-- --><!-- --><!-- --></li><!-- --><!-- --><li _ngcontent-vc-app-c187=\"\">Color:<!-- --> Burgundy </li><!-- --><!-- --><li _ngcontent-vc-app-c187=\"\">Size:<!-- --> 38 FR <button _ngcontent-vc-app-c187=\"\" class=\"productDetails__moreInfoLink vc-link vc-text-m\">sizing guide</button><!-- --></li><!-- --><!-- --><li _ngcontent-vc-app-c187=\"\">Location:<!-- -->France,\n          from\n          the seller Not<!-- --><!-- --></li><!-- --><li _ngcontent-vc-app-c187=\"\">Reference:<!-- --> 19164267</li></ul>"}, {"id": 19168094, "url": "https://fr.vestiairecollective.com//women-bags/handbags/jean-paul-gaultier/brown-leather-jean-paul-gaultier-handbag-19168094.shtml", "brand": "jean-paul-gaultier", "page_no": 0, "description": "<ul _ngcontent-vc-app-c187=\"\" class=\"descriptionList__block__list descriptionList__block__list--detail\"><li _ngcontent-vc-app-c187=\"\">Online since:<!-- --> 11/11/2021 </li><li _ngcontent-vc-app-c187=\"\">Categories : <!-- --> Women </li><li _ngcontent-vc-app-c187=\"\">Category:<!-- --> Bags </li><li _ngcontent-vc-app-c187=\"\">Sub-category:<!-- --> Handbags </li><!-- --><li _ngcontent-vc-app-c187=\"\">Designer:<!-- --> Jean Paul Gaultier </li><!-- --><li _ngcontent-vc-app-c187=\"\"><span _ngcontent-vc-app-c187=\"\">Condition:<!-- --> Never worn</span><button _ngcontent-vc-app-c187=\"\" class=\"descriptionList__block__list__moreInfo vc-link vc-text-m\">More info</button></li><li _ngcontent-vc-app-c187=\"\">Material:<!-- --> Leather <!-- --><!-- --><!-- --><!-- --></li><!-- --><!-- --><li _ngcontent-vc-app-c187=\"\">Color:<!-- --> Brown </li><!-- --><!-- --><!-- --><li _ngcontent-vc-app-c187=\"\">Style:<!-- -->Vintage<!-- --></li><!-- --><li _ngcontent-vc-app-c187=\"\">Location:<!-- -->France,\n          from\n          the seller C\u00e9line<!-- --><!-- --></li><!-- --><li _ngcontent-vc-app-c187=\"\">Reference:<!-- --> 19168094</li></ul>"}, {"id": 19168416, "url": "https://fr.vestiairecollective.com//women-bags/handbags/jean-paul-gaultier/brown-leather-jean-paul-gaultier-handbag-19168416.shtml", "brand": "jean-paul-gaultier", "page_no": 0, "description": "<ul _ngcontent-vc-app-c187=\"\" class=\"descriptionList__block__list descriptionList__block__list--detail\"><li _ngcontent-vc-app-c187=\"\">Online since:<!-- --> 11/11/2021 </li><li _ngcontent-vc-app-c187=\"\">Categories : <!-- --> Women </li><li _ngcontent-vc-app-c187=\"\">Category:<!-- --> Bags </li><li _ngcontent-vc-app-c187=\"\">Sub-category:<!-- --> Handbags </li><!-- --><li _ngcontent-vc-app-c187=\"\">Designer:<!-- --> Jean Paul Gaultier </li><!-- --><li _ngcontent-vc-app-c187=\"\"><span _ngcontent-vc-app-c187=\"\">Condition:<!-- --> Never worn</span><button _ngcontent-vc-app-c187=\"\" class=\"descriptionList__block__list__moreInfo vc-link vc-text-m\">More info</button></li><li _ngcontent-vc-app-c187=\"\">Material:<!-- --> Leather <!-- --><!-- --><!-- --><!-- --></li><!-- --><!-- --><li _ngcontent-vc-app-c187=\"\">Color:<!-- --> Brown </li><!-- --><!-- --><!-- --><!-- --><li _ngcontent-vc-app-c187=\"\">Location:<!-- -->France,\n          from\n          the seller C\u00e9line<!-- --><!-- --></li><!-- --><li _ngcontent-vc-app-c187=\"\">Reference:<!-- --> 19168416</li></ul>"}, {"id": 19169710, "url": "https://fr.vestiairecollective.com//men-clothing/jackets/jean-paul-gaultier/navy-wool-jean-paul-gaultier-jacket-19169710.shtml", "brand": "jean-paul-gaultier", "page_no": 0, "description": "<ul _ngcontent-vc-app-c187=\"\" class=\"descriptionList__block__list descriptionList__block__list--detail\"><li _ngcontent-vc-app-c187=\"\">Online since:<!-- --> 11/11/2021 </li><li _ngcontent-vc-app-c187=\"\">Categories : <!-- --> Men </li><li _ngcontent-vc-app-c187=\"\">Category:<!-- --> Clothing </li><li _ngcontent-vc-app-c187=\"\">Sub-category:<!-- --> Jackets  </li><!-- --><li _ngcontent-vc-app-c187=\"\">Designer:<!-- --> Jean Paul Gaultier </li><!-- --><li _ngcontent-vc-app-c187=\"\"><span _ngcontent-vc-app-c187=\"\">Condition:<!-- --> Very good condition</span><button _ngcontent-vc-app-c187=\"\" class=\"descriptionList__block__list__moreInfo vc-link vc-text-m\">More info</button></li><li _ngcontent-vc-app-c187=\"\">Material:<!-- --> Wool <!-- --><!-- --><!-- --><!-- --></li><!-- --><!-- --><li _ngcontent-vc-app-c187=\"\">Color:<!-- --> Navy </li><!-- --><!-- --><li _ngcontent-vc-app-c187=\"\">Size:<!-- --> 54 IT <button _ngcontent-vc-app-c187=\"\" class=\"productDetails__moreInfoLink vc-link vc-text-m\">sizing guide</button><!-- --></li><!-- --><!-- --><li _ngcontent-vc-app-c187=\"\">Location:<!-- -->France,\n          from\n          the seller Jack <!-- --><!-- --></li><!-- --><li _ngcontent-vc-app-c187=\"\">Reference:<!-- --> 19169710</li></ul>"}, {"id": 19170141, "url": "https://fr.vestiairecollective.com//women-clothing/knitwear/jean-paul-gaultier/anthracite-wool-jean-paul-gaultier-knitwear-19170141.shtml", "brand": "jean-paul-gaultier", "page_no": 0, "description": "<ul _ngcontent-vc-app-c187=\"\" class=\"descriptionList__block__list descriptionList__block__list--detail\"><li _ngcontent-vc-app-c187=\"\">Online since:<!-- --> 11/11/2021 </li><li _ngcontent-vc-app-c187=\"\">Categories : <!-- --> Women </li><li _ngcontent-vc-app-c187=\"\">Category:<!-- --> Clothing </li><li _ngcontent-vc-app-c187=\"\">Sub-category:<!-- --> Knitwear </li><!-- --><li _ngcontent-vc-app-c187=\"\">Designer:<!-- --> Jean Paul Gaultier </li><!-- --><li _ngcontent-vc-app-c187=\"\"><span _ngcontent-vc-app-c187=\"\">Condition:<!-- --> Very good condition</span><button _ngcontent-vc-app-c187=\"\" class=\"descriptionList__block__list__moreInfo vc-link vc-text-m\">More info</button></li><li _ngcontent-vc-app-c187=\"\">Material:<!-- --> Wool <!-- --><!-- --><!-- --><!-- --></li><!-- --><!-- --><li _ngcontent-vc-app-c187=\"\">Color:<!-- --> Anthracite </li><!-- --><!-- --><li _ngcontent-vc-app-c187=\"\">Size:<!-- --> 46 IT <button _ngcontent-vc-app-c187=\"\" class=\"productDetails__moreInfoLink vc-link vc-text-m\">sizing guide</button><!-- --></li><!-- --><li _ngcontent-vc-app-c187=\"\">Style:<!-- -->Vintage<!-- --></li><!-- --><li _ngcontent-vc-app-c187=\"\">Location:<!-- -->Italy,\n          from\n          the seller Francesca<!-- --><!-- --></li><!-- --><li _ngcontent-vc-app-c187=\"\">Reference:<!-- --> 19170141</li></ul>"}, {"id": 19149787, "url": "https://fr.vestiairecollective.com//women-clothing/dresses/jean-paul-gaultier/grey-viscose-jean-paul-gaultier-dress-19149787.shtml", "brand": "jean-paul-gaultier", "page_no": 0, "description": "<ul _ngcontent-vc-app-c187=\"\" class=\"descriptionList__block__list descriptionList__block__list--detail\"><li _ngcontent-vc-app-c187=\"\">Online since:<!-- --> 10/11/2021 </li><li _ngcontent-vc-app-c187=\"\">Categories : <!-- --> Women </li><li _ngcontent-vc-app-c187=\"\">Category:<!-- --> Clothing </li><li _ngcontent-vc-app-c187=\"\">Sub-category:<!-- --> Dresses </li><!-- --><li _ngcontent-vc-app-c187=\"\">Designer:<!-- --> Jean Paul Gaultier </li><!-- --><li _ngcontent-vc-app-c187=\"\"><span _ngcontent-vc-app-c187=\"\">Condition:<!-- --> Very good condition</span><button _ngcontent-vc-app-c187=\"\" class=\"descriptionList__block__list__moreInfo vc-link vc-text-m\">More info</button></li><li _ngcontent-vc-app-c187=\"\">Material:<!-- --> Viscose <!-- --><!-- --><!-- --><!-- --></li><!-- --><!-- --><li _ngcontent-vc-app-c187=\"\">Color:<!-- --> Grey </li><!-- --><!-- --><li _ngcontent-vc-app-c187=\"\">Size:<!-- --> 42 IT <button _ngcontent-vc-app-c187=\"\" class=\"productDetails__moreInfoLink vc-link vc-text-m\">sizing guide</button><!-- --></li><!-- --><!-- --><li _ngcontent-vc-app-c187=\"\">Location:<!-- -->Italy,\n          from\n          the seller giovanna<!-- --><!-- --></li><!-- --><li _ngcontent-vc-app-c187=\"\">Reference:<!-- --> 19149787</li></ul>"}, {"id": 19059679, "url": "https://fr.vestiairecollective.com//women-clothing/tops/jean-paul-gaultier/multicolour-synthetic-jean-paul-gaultier-top-19059679.shtml", "brand": "jean-paul-gaultier", "page_no": 0, "description": "<ul _ngcontent-vc-app-c187=\"\" class=\"descriptionList__block__list descriptionList__block__list--detail\"><li _ngcontent-vc-app-c187=\"\">Online since:<!-- --> 06/11/2021 </li><li _ngcontent-vc-app-c187=\"\">Categories : <!-- --> Women </li><li _ngcontent-vc-app-c187=\"\">Category:<!-- --> Clothing </li><li _ngcontent-vc-app-c187=\"\">Sub-category:<!-- --> Tops </li><!-- --><li _ngcontent-vc-app-c187=\"\">Designer:<!-- --> Jean Paul Gaultier </li><!-- --><li _ngcontent-vc-app-c187=\"\"><span _ngcontent-vc-app-c187=\"\">Condition:<!-- --> Very good condition</span><button _ngcontent-vc-app-c187=\"\" class=\"descriptionList__block__list__moreInfo vc-link vc-text-m\">More info</button></li><li _ngcontent-vc-app-c187=\"\">Material:<!-- --> Synthetic <!-- --><!-- --><!-- --><!-- --></li><!-- --><!-- --><li _ngcontent-vc-app-c187=\"\">Color:<!-- --> Multicolour </li><!-- --><!-- --><li _ngcontent-vc-app-c187=\"\">Size:<!-- --> L International <button _ngcontent-vc-app-c187=\"\" class=\"productDetails__moreInfoLink vc-link vc-text-m\">sizing guide</button><!-- --></li><!-- --><!-- --><li _ngcontent-vc-app-c187=\"\">Location:<!-- -->Italy,\n          from\n          the seller adele<!-- --><!-- --></li><!-- --><li _ngcontent-vc-app-c187=\"\">Reference:<!-- --> 19059679</li></ul>"}, {"id": 19087881, "url": "https://fr.vestiairecollective.com//women-clothing/jackets/jean-paul-gaultier/red-cotton-jean-paul-gaultier-jacket-19087881.shtml", "brand": "jean-paul-gaultier", "page_no": 0, "description": "<ul _ngcontent-vc-app-c187=\"\" class=\"descriptionList__block__list descriptionList__block__list--detail\"><li _ngcontent-vc-app-c187=\"\">Online since:<!-- --> 07/11/2021 </li><li _ngcontent-vc-app-c187=\"\">Categories : <!-- --> Women </li><li _ngcontent-vc-app-c187=\"\">Category:<!-- --> Clothing </li><li _ngcontent-vc-app-c187=\"\">Sub-category:<!-- --> Jackets </li><!-- --><li _ngcontent-vc-app-c187=\"\">Designer:<!-- --> Jean Paul Gaultier </li><!-- --><li _ngcontent-vc-app-c187=\"\"><span _ngcontent-vc-app-c187=\"\">Condition:<!-- --> Never worn</span><button _ngcontent-vc-app-c187=\"\" class=\"descriptionList__block__list__moreInfo vc-link vc-text-m\">More info</button></li><li _ngcontent-vc-app-c187=\"\">Material:<!-- --> Cotton <!-- --><!-- --><!-- --><!-- --></li><!-- --><!-- --><li _ngcontent-vc-app-c187=\"\">Color:<!-- --> Red </li><!-- --><!-- --><li _ngcontent-vc-app-c187=\"\">Size:<!-- --> 42 IT <button _ngcontent-vc-app-c187=\"\" class=\"productDetails__moreInfoLink vc-link vc-text-m\">sizing guide</button><!-- --></li><!-- --><!-- --><li _ngcontent-vc-app-c187=\"\">Location:<!-- -->Italy,\n          from\n          the seller tania<!-- --><!-- --></li><!-- --><li _ngcontent-vc-app-c187=\"\">Reference:<!-- --> 19087881</li></ul>"}, {"id": 19072965, "url": "https://fr.vestiairecollective.com//women-clothing/dresses/jean-paul-gaultier/black-denim-jeans-jean-paul-gaultier-dress-19072965.shtml", "brand": "jean-paul-gaultier", "page_no": 0, "description": "<ul _ngcontent-vc-app-c187=\"\" class=\"descriptionList__block__list descriptionList__block__list--detail\"><li _ngcontent-vc-app-c187=\"\">Online since:<!-- --> 07/11/2021 </li><li _ngcontent-vc-app-c187=\"\">Categories : <!-- --> Women </li><li _ngcontent-vc-app-c187=\"\">Category:<!-- --> Clothing </li><li _ngcontent-vc-app-c187=\"\">Sub-category:<!-- --> Dresses </li><!-- --><li _ngcontent-vc-app-c187=\"\">Designer:<!-- --> Jean Paul Gaultier </li><!-- --><li _ngcontent-vc-app-c187=\"\"><span _ngcontent-vc-app-c187=\"\">Condition:<!-- --> Very good condition</span><button _ngcontent-vc-app-c187=\"\" class=\"descriptionList__block__list__moreInfo vc-link vc-text-m\">More info</button></li><li _ngcontent-vc-app-c187=\"\">Material:<!-- --> Denim - Jeans <!-- --><!-- --><!-- --><!-- --></li><!-- --><!-- --><li _ngcontent-vc-app-c187=\"\">Color:<!-- --> Black </li><!-- --><!-- --><li _ngcontent-vc-app-c187=\"\">Size:<!-- --> 44 IT <button _ngcontent-vc-app-c187=\"\" class=\"productDetails__moreInfoLink vc-link vc-text-m\">sizing guide</button><!-- --></li><!-- --><!-- --><li _ngcontent-vc-app-c187=\"\">Location:<!-- -->Spain,\n          from\n          the seller catalina <!-- --><!-- --></li><!-- --><li _ngcontent-vc-app-c187=\"\">Reference:<!-- --> 19072965</li></ul>"}, {"id": 19056290, "url": "https://fr.vestiairecollective.com//women-clothing/tops/jean-paul-gaultier/orange-polyester-jean-paul-gaultier-top-19056290.shtml", "brand": "jean-paul-gaultier", "page_no": 0, "description": "<ul _ngcontent-vc-app-c187=\"\" class=\"descriptionList__block__list descriptionList__block__list--detail\"><li _ngcontent-vc-app-c187=\"\">Online since:<!-- --> 06/11/2021 </li><li _ngcontent-vc-app-c187=\"\">Categories : <!-- --> Women </li><li _ngcontent-vc-app-c187=\"\">Category:<!-- --> Clothing </li><li _ngcontent-vc-app-c187=\"\">Sub-category:<!-- --> Tops </li><!-- --><li _ngcontent-vc-app-c187=\"\">Designer:<!-- --> Jean Paul Gaultier </li><!-- --><li _ngcontent-vc-app-c187=\"\"><span _ngcontent-vc-app-c187=\"\">Condition:<!-- --> Very good condition</span><button _ngcontent-vc-app-c187=\"\" class=\"descriptionList__block__list__moreInfo vc-link vc-text-m\">More info</button></li><li _ngcontent-vc-app-c187=\"\">Material:<!-- --> Polyester <!-- --><!-- --><!-- --><!-- --></li><!-- --><!-- --><li _ngcontent-vc-app-c187=\"\">Color:<!-- --> Orange </li><!-- --><!-- --><li _ngcontent-vc-app-c187=\"\">Size:<!-- --> S International <button _ngcontent-vc-app-c187=\"\" class=\"productDetails__moreInfoLink vc-link vc-text-m\">sizing guide</button><!-- --></li><!-- --><li _ngcontent-vc-app-c187=\"\">Style:<!-- -->Vintage<!-- --></li><!-- --><li _ngcontent-vc-app-c187=\"\">Location:<!-- -->Italy,\n          from\n          the seller monica<!-- --><!-- --></li><!-- --><li _ngcontent-vc-app-c187=\"\">Reference:<!-- --> 19056290</li></ul>"}, {"id": 19185443, "url": "https://fr.vestiairecollective.com//men-clothing/t-shirts/jean-paul-gaultier/beige-synthetic-jean-paul-gaultier-t-shirt-19185443.shtml", "brand": "jean-paul-gaultier", "page_no": 0, "description": "<ul _ngcontent-vc-app-c187=\"\" class=\"descriptionList__block__list descriptionList__block__list--detail\"><li _ngcontent-vc-app-c187=\"\">Online since:<!-- --> 12/11/2021 </li><li _ngcontent-vc-app-c187=\"\">Categories : <!-- --> Men </li><li _ngcontent-vc-app-c187=\"\">Category:<!-- --> Clothing </li><li _ngcontent-vc-app-c187=\"\">Sub-category:<!-- --> T-shirts </li><!-- --><li _ngcontent-vc-app-c187=\"\">Designer:<!-- --> Jean Paul Gaultier </li><!-- --><li _ngcontent-vc-app-c187=\"\"><span _ngcontent-vc-app-c187=\"\">Condition:<!-- --> Good condition</span><button _ngcontent-vc-app-c187=\"\" class=\"descriptionList__block__list__moreInfo vc-link vc-text-m\">More info</button></li><li _ngcontent-vc-app-c187=\"\">Material:<!-- --> Synthetic <!-- --><!-- --><!-- --><!-- --></li><!-- --><!-- --><li _ngcontent-vc-app-c187=\"\">Color:<!-- --> Beige </li><!-- --><!-- --><li _ngcontent-vc-app-c187=\"\">Size:<!-- --> L International <button _ngcontent-vc-app-c187=\"\" class=\"productDetails__moreInfoLink vc-link vc-text-m\">sizing guide</button><!-- --></li><!-- --><li _ngcontent-vc-app-c187=\"\">Style:<!-- -->Vintage<!-- --></li><!-- --><li _ngcontent-vc-app-c187=\"\">Location:<!-- -->Italy,\n          from\n          the seller Eliz  <!-- --><!-- --></li><!-- --><li _ngcontent-vc-app-c187=\"\">Reference:<!-- --> 19185443</li></ul>"}, {"id": 19080339, "url": "https://fr.vestiairecollective.com//women-clothing/tops/jean-paul-gaultier/white-cotton-jean-paul-gaultier-top-19080339.shtml", "brand": "jean-paul-gaultier", "page_no": 0, "description": "<ul _ngcontent-vc-app-c187=\"\" class=\"descriptionList__block__list descriptionList__block__list--detail\"><li _ngcontent-vc-app-c187=\"\">Online since:<!-- --> 07/11/2021 </li><li _ngcontent-vc-app-c187=\"\">Categories : <!-- --> Women </li><li _ngcontent-vc-app-c187=\"\">Category:<!-- --> Clothing </li><li _ngcontent-vc-app-c187=\"\">Sub-category:<!-- --> Tops </li><!-- --><li _ngcontent-vc-app-c187=\"\">Designer:<!-- --> Jean Paul Gaultier </li><!-- --><li _ngcontent-vc-app-c187=\"\"><span _ngcontent-vc-app-c187=\"\">Condition:<!-- --> Good condition</span><button _ngcontent-vc-app-c187=\"\" class=\"descriptionList__block__list__moreInfo vc-link vc-text-m\">More info</button></li><li _ngcontent-vc-app-c187=\"\">Material:<!-- --> Cotton <!-- --><!-- --><!-- --><!-- --></li><!-- --><!-- --><li _ngcontent-vc-app-c187=\"\">Color:<!-- --> White </li><!-- --><!-- --><li _ngcontent-vc-app-c187=\"\">Size:<!-- --> 38 FR <button _ngcontent-vc-app-c187=\"\" class=\"productDetails__moreInfoLink vc-link vc-text-m\">sizing guide</button><!-- --></li><!-- --><li _ngcontent-vc-app-c187=\"\">Style:<!-- -->Vintage<!-- --></li><!-- --><li _ngcontent-vc-app-c187=\"\">Location:<!-- -->Spain,\n          from\n          the seller RUBEN<!-- --><!-- --></li><!-- --><li _ngcontent-vc-app-c187=\"\">Reference:<!-- --> 19080339</li></ul>"}, {"id": 19055404, "url": "https://fr.vestiairecollective.com//women-clothing/skirts/jean-paul-gaultier/multicolour-synthetic-jean-paul-gaultier-skirt-19055404.shtml", "brand": "jean-paul-gaultier", "page_no": 0, "description": "<ul _ngcontent-vc-app-c187=\"\" class=\"descriptionList__block__list descriptionList__block__list--detail\"><li _ngcontent-vc-app-c187=\"\">Online since:<!-- --> 06/11/2021 </li><li _ngcontent-vc-app-c187=\"\">Categories : <!-- --> Women </li><li _ngcontent-vc-app-c187=\"\">Category:<!-- --> Clothing </li><li _ngcontent-vc-app-c187=\"\">Sub-category:<!-- --> Skirts </li><!-- --><li _ngcontent-vc-app-c187=\"\">Designer:<!-- --> Jean Paul Gaultier </li><!-- --><li _ngcontent-vc-app-c187=\"\"><span _ngcontent-vc-app-c187=\"\">Condition:<!-- --> Never worn</span><button _ngcontent-vc-app-c187=\"\" class=\"descriptionList__block__list__moreInfo vc-link vc-text-m\">More info</button></li><li _ngcontent-vc-app-c187=\"\">Material:<!-- --> Synthetic <!-- --><!-- --><!-- --><!-- --></li><!-- --><!-- --><li _ngcontent-vc-app-c187=\"\">Color:<!-- --> Multicolour </li><!-- --><!-- --><li _ngcontent-vc-app-c187=\"\">Size:<!-- --> S International <button _ngcontent-vc-app-c187=\"\" class=\"productDetails__moreInfoLink vc-link vc-text-m\">sizing guide</button><!-- --></li><!-- --><li _ngcontent-vc-app-c187=\"\">Style:<!-- -->Vintage<!-- --></li><!-- --><li _ngcontent-vc-app-c187=\"\">Location:<!-- -->Italy,\n          from\n          the seller Emilia<!-- --><!-- --></li><!-- --><li _ngcontent-vc-app-c187=\"\">Reference:<!-- --> 19055404</li></ul>"}, {"id": 19185759, "url": "https://fr.vestiairecollective.com//women-clothing/jackets/jean-paul-gaultier/black-synthetic-jean-paul-gaultier-jacket-19185759.shtml", "brand": "jean-paul-gaultier", "page_no": 0, "description": "<ul _ngcontent-vc-app-c187=\"\" class=\"descriptionList__block__list descriptionList__block__list--detail\"><li _ngcontent-vc-app-c187=\"\">Online since:<!-- --> 12/11/2021 </li><li _ngcontent-vc-app-c187=\"\">Categories : <!-- --> Women </li><li _ngcontent-vc-app-c187=\"\">Category:<!-- --> Clothing </li><li _ngcontent-vc-app-c187=\"\">Sub-category:<!-- --> Jackets </li><!-- --><li _ngcontent-vc-app-c187=\"\">Designer:<!-- --> Jean Paul Gaultier </li><!-- --><li _ngcontent-vc-app-c187=\"\"><span _ngcontent-vc-app-c187=\"\">Condition:<!-- --> Fair condition</span><button _ngcontent-vc-app-c187=\"\" class=\"descriptionList__block__list__moreInfo vc-link vc-text-m\">More info</button></li><li _ngcontent-vc-app-c187=\"\">Material:<!-- --> Synthetic <!-- --><!-- --><!-- --><!-- --></li><!-- --><!-- --><li _ngcontent-vc-app-c187=\"\">Color:<!-- --> Black </li><!-- --><!-- --><li _ngcontent-vc-app-c187=\"\">Size:<!-- --> 42 IT <button _ngcontent-vc-app-c187=\"\" class=\"productDetails__moreInfoLink vc-link vc-text-m\">sizing guide</button><!-- --></li><!-- --><li _ngcontent-vc-app-c187=\"\">Style:<!-- -->Vintage<!-- --></li><!-- --><li _ngcontent-vc-app-c187=\"\">Location:<!-- -->Italy,\n          from\n          the seller Eliz  <!-- --><!-- --></li><!-- --><li _ngcontent-vc-app-c187=\"\">Reference:<!-- --> 19185759</li></ul>"}, {"id": 19069218, "url": "https://fr.vestiairecollective.com//women-clothing/tops/jean-paul-gaultier/purple-silk-jean-paul-gaultier-top-19069218.shtml", "brand": "jean-paul-gaultier", "page_no": 0, "description": "<ul _ngcontent-vc-app-c187=\"\" class=\"descriptionList__block__list descriptionList__block__list--detail\"><li _ngcontent-vc-app-c187=\"\">Online since:<!-- --> 07/11/2021 </li><li _ngcontent-vc-app-c187=\"\">Categories : <!-- --> Women </li><li _ngcontent-vc-app-c187=\"\">Category:<!-- --> Clothing </li><li _ngcontent-vc-app-c187=\"\">Sub-category:<!-- --> Tops </li><!-- --><li _ngcontent-vc-app-c187=\"\">Designer:<!-- --> Jean Paul Gaultier </li><!-- --><li _ngcontent-vc-app-c187=\"\"><span _ngcontent-vc-app-c187=\"\">Condition:<!-- --> Very good condition</span><button _ngcontent-vc-app-c187=\"\" class=\"descriptionList__block__list__moreInfo vc-link vc-text-m\">More info</button></li><li _ngcontent-vc-app-c187=\"\">Material:<!-- --> Silk <!-- --><!-- --><!-- --><!-- --></li><!-- --><!-- --><li _ngcontent-vc-app-c187=\"\">Color:<!-- --> Purple </li><!-- --><!-- --><li _ngcontent-vc-app-c187=\"\">Size:<!-- --> 38 FR <button _ngcontent-vc-app-c187=\"\" class=\"productDetails__moreInfoLink vc-link vc-text-m\">sizing guide</button><!-- --></li><!-- --><!-- --><li _ngcontent-vc-app-c187=\"\">Location:<!-- -->France,\n          from\n          the seller Rebecca<!-- --><!-- --></li><!-- --><li _ngcontent-vc-app-c187=\"\">Reference:<!-- --> 19069218</li></ul>"}, {"id": 19103610, "url": "https://fr.vestiairecollective.com//women-clothing/skirts/jean-paul-gaultier/purple-viscose-jean-paul-gaultier-skirt-19103610.shtml", "brand": "jean-paul-gaultier", "page_no": 0, "description": "<ul _ngcontent-vc-app-c187=\"\" class=\"descriptionList__block__list descriptionList__block__list--detail\"><li _ngcontent-vc-app-c187=\"\">Online since:<!-- --> 08/11/2021 </li><li _ngcontent-vc-app-c187=\"\">Categories : <!-- --> Women </li><li _ngcontent-vc-app-c187=\"\">Category:<!-- --> Clothing </li><li _ngcontent-vc-app-c187=\"\">Sub-category:<!-- --> Skirts </li><!-- --><li _ngcontent-vc-app-c187=\"\">Designer:<!-- --> Jean Paul Gaultier </li><!-- --><li _ngcontent-vc-app-c187=\"\"><span _ngcontent-vc-app-c187=\"\">Condition:<!-- --> Very good condition</span><button _ngcontent-vc-app-c187=\"\" class=\"descriptionList__block__list__moreInfo vc-link vc-text-m\">More info</button></li><li _ngcontent-vc-app-c187=\"\">Material:<!-- --> Viscose <!-- --><!-- --><!-- --><!-- --></li><!-- --><!-- --><li _ngcontent-vc-app-c187=\"\">Color:<!-- --> Purple </li><!-- --><!-- --><li _ngcontent-vc-app-c187=\"\">Size:<!-- --> 36 FR <button _ngcontent-vc-app-c187=\"\" class=\"productDetails__moreInfoLink vc-link vc-text-m\">sizing guide</button><!-- --></li><!-- --><li _ngcontent-vc-app-c187=\"\">Style:<!-- -->Vintage<!-- --></li><!-- --><li _ngcontent-vc-app-c187=\"\">Location:<!-- -->France,\n          from\n          the seller The <!-- --><!-- --></li><!-- --><li _ngcontent-vc-app-c187=\"\">Reference:<!-- --> 19103610</li></ul>"}, {"id": 18944204, "url": "https://fr.vestiairecollective.com//women-clothing/dresses/jean-paul-gaultier/multicolour-synthetic-jean-paul-gaultier-dress-18944204.shtml", "brand": "jean-paul-gaultier", "page_no": 0, "description": "<ul _ngcontent-vc-app-c187=\"\" class=\"descriptionList__block__list descriptionList__block__list--detail\"><li _ngcontent-vc-app-c187=\"\">Online since:<!-- --> 31/10/2021 </li><li _ngcontent-vc-app-c187=\"\">Categories : <!-- --> Women </li><li _ngcontent-vc-app-c187=\"\">Category:<!-- --> Clothing </li><li _ngcontent-vc-app-c187=\"\">Sub-category:<!-- --> Dresses </li><!-- --><li _ngcontent-vc-app-c187=\"\">Designer:<!-- --> Jean Paul Gaultier </li><!-- --><li _ngcontent-vc-app-c187=\"\"><span _ngcontent-vc-app-c187=\"\">Condition:<!-- --> Never worn</span><button _ngcontent-vc-app-c187=\"\" class=\"descriptionList__block__list__moreInfo vc-link vc-text-m\">More info</button></li><li _ngcontent-vc-app-c187=\"\">Material:<!-- --> Synthetic <!-- --><!-- --><!-- --><!-- --></li><!-- --><!-- --><li _ngcontent-vc-app-c187=\"\">Color:<!-- --> Multicolour </li><!-- --><!-- --><li _ngcontent-vc-app-c187=\"\">Size:<!-- --> S International <button _ngcontent-vc-app-c187=\"\" class=\"productDetails__moreInfoLink vc-link vc-text-m\">sizing guide</button><!-- --></li><!-- --><!-- --><li _ngcontent-vc-app-c187=\"\">Location:<!-- -->Italy,\n          from\n          the seller Sepa<!-- --><!-- --></li><!-- --><li _ngcontent-vc-app-c187=\"\">Reference:<!-- --> 18944204</li></ul>"}, {"id": 18935273, "url": "https://fr.vestiairecollective.com//women-clothing/dresses/jean-paul-gaultier/multicolour-viscose-jean-paul-gaultier-dress-18935273.shtml", "brand": "jean-paul-gaultier", "page_no": 0, "description": "<ul _ngcontent-vc-app-c187=\"\" class=\"descriptionList__block__list descriptionList__block__list--detail\"><li _ngcontent-vc-app-c187=\"\">Online since:<!-- --> 31/10/2021 </li><li _ngcontent-vc-app-c187=\"\">Categories : <!-- --> Women </li><li _ngcontent-vc-app-c187=\"\">Category:<!-- --> Clothing </li><li _ngcontent-vc-app-c187=\"\">Sub-category:<!-- --> Dresses </li><!-- --><li _ngcontent-vc-app-c187=\"\">Designer:<!-- --> Jean Paul Gaultier </li><!-- --><li _ngcontent-vc-app-c187=\"\"><span _ngcontent-vc-app-c187=\"\">Condition:<!-- --> Very good condition</span><button _ngcontent-vc-app-c187=\"\" class=\"descriptionList__block__list__moreInfo vc-link vc-text-m\">More info</button></li><li _ngcontent-vc-app-c187=\"\">Material:<!-- --> Viscose <!-- --><!-- --><!-- --><!-- --></li><!-- --><!-- --><li _ngcontent-vc-app-c187=\"\">Color:<!-- --> Multicolour </li><!-- --><!-- --><li _ngcontent-vc-app-c187=\"\">Size:<!-- --> S International <button _ngcontent-vc-app-c187=\"\" class=\"productDetails__moreInfoLink vc-link vc-text-m\">sizing guide</button><!-- --></li><!-- --><!-- --><li _ngcontent-vc-app-c187=\"\">Location:<!-- -->Italy,\n          from\n          the seller Roberta<!-- --><!-- --></li><!-- --><li _ngcontent-vc-app-c187=\"\">Reference:<!-- --> 18935273</li></ul>"}, {"id": 18943474, "url": "https://fr.vestiairecollective.com//women-clothing/tops/jean-paul-gaultier/multicolour-polyester-jean-paul-gaultier-top-18943474.shtml", "brand": "jean-paul-gaultier", "page_no": 0, "description": "<ul _ngcontent-vc-app-c187=\"\" class=\"descriptionList__block__list descriptionList__block__list--detail\"><li _ngcontent-vc-app-c187=\"\">Online since:<!-- --> 31/10/2021 </li><li _ngcontent-vc-app-c187=\"\">Categories : <!-- --> Women </li><li _ngcontent-vc-app-c187=\"\">Category:<!-- --> Clothing </li><li _ngcontent-vc-app-c187=\"\">Sub-category:<!-- --> Tops </li><!-- --><li _ngcontent-vc-app-c187=\"\">Designer:<!-- --> Jean Paul Gaultier </li><!-- --><li _ngcontent-vc-app-c187=\"\"><span _ngcontent-vc-app-c187=\"\">Condition:<!-- --> Very good condition</span><button _ngcontent-vc-app-c187=\"\" class=\"descriptionList__block__list__moreInfo vc-link vc-text-m\">More info</button></li><li _ngcontent-vc-app-c187=\"\">Material:<!-- --> Polyester <!-- --><!-- --><!-- --><!-- --></li><!-- --><!-- --><li _ngcontent-vc-app-c187=\"\">Color:<!-- --> Multicolour </li><!-- --><!-- --><li _ngcontent-vc-app-c187=\"\">Size:<!-- --> XS International <button _ngcontent-vc-app-c187=\"\" class=\"productDetails__moreInfoLink vc-link vc-text-m\">sizing guide</button><!-- --></li><!-- --><li _ngcontent-vc-app-c187=\"\">Style:<!-- -->Vintage<!-- --></li><!-- --><li _ngcontent-vc-app-c187=\"\">Location:<!-- -->Bulgaria,\n          from\n          the seller Daniela<!-- --><!-- --></li><!-- --><li _ngcontent-vc-app-c187=\"\">Reference:<!-- --> 18943474</li></ul>"}, {"id": 18874184, "url": "https://fr.vestiairecollective.com//women-clothing/tops/jean-paul-gaultier/multicolour-polyester-jean-paul-gaultier-top-18874184.shtml", "brand": "jean-paul-gaultier", "page_no": 0, "description": "<ul _ngcontent-vc-app-c187=\"\" class=\"descriptionList__block__list descriptionList__block__list--detail\"><li _ngcontent-vc-app-c187=\"\">Online since:<!-- --> 29/10/2021 </li><li _ngcontent-vc-app-c187=\"\">Categories : <!-- --> Women </li><li _ngcontent-vc-app-c187=\"\">Category:<!-- --> Clothing </li><li _ngcontent-vc-app-c187=\"\">Sub-category:<!-- --> Tops </li><!-- --><li _ngcontent-vc-app-c187=\"\">Designer:<!-- --> Jean Paul Gaultier </li><!-- --><li _ngcontent-vc-app-c187=\"\"><span _ngcontent-vc-app-c187=\"\">Condition:<!-- --> Very good condition</span><button _ngcontent-vc-app-c187=\"\" class=\"descriptionList__block__list__moreInfo vc-link vc-text-m\">More info</button></li><li _ngcontent-vc-app-c187=\"\">Material:<!-- --> Polyester <!-- --><!-- --><!-- --><!-- --></li><!-- --><!-- --><li _ngcontent-vc-app-c187=\"\">Color:<!-- --> Multicolour </li><!-- --><!-- --><li _ngcontent-vc-app-c187=\"\">Size:<!-- --> L International <button _ngcontent-vc-app-c187=\"\" class=\"productDetails__moreInfoLink vc-link vc-text-m\">sizing guide</button><!-- --></li><!-- --><!-- --><li _ngcontent-vc-app-c187=\"\">Location:<!-- -->Spain,\n          from\n          the seller RUBEN<!-- --><!-- --></li><!-- --><li _ngcontent-vc-app-c187=\"\">Reference:<!-- --> 18874184</li></ul>"}, {"id": 18896043, "url": "https://fr.vestiairecollective.com//women-clothing/dresses/jean-paul-gaultier/turquoise-synthetic-jean-paul-gaultier-dress-18896043.shtml", "brand": "jean-paul-gaultier", "page_no": 0, "description": "<ul _ngcontent-vc-app-c187=\"\" class=\"descriptionList__block__list descriptionList__block__list--detail\"><li _ngcontent-vc-app-c187=\"\">Online since:<!-- --> 29/10/2021 </li><li _ngcontent-vc-app-c187=\"\">Categories : <!-- --> Women </li><li _ngcontent-vc-app-c187=\"\">Category:<!-- --> Clothing </li><li _ngcontent-vc-app-c187=\"\">Sub-category:<!-- --> Dresses </li><!-- --><li _ngcontent-vc-app-c187=\"\">Designer:<!-- --> Jean Paul Gaultier </li><!-- --><li _ngcontent-vc-app-c187=\"\"><span _ngcontent-vc-app-c187=\"\">Condition:<!-- --> Never worn</span><button _ngcontent-vc-app-c187=\"\" class=\"descriptionList__block__list__moreInfo vc-link vc-text-m\">More info</button></li><li _ngcontent-vc-app-c187=\"\">Material:<!-- --> Synthetic <!-- --><!-- --><!-- --><!-- --></li><!-- --><!-- --><li _ngcontent-vc-app-c187=\"\">Color:<!-- --> Turquoise </li><!-- --><!-- --><li _ngcontent-vc-app-c187=\"\">Size:<!-- --> M International <button _ngcontent-vc-app-c187=\"\" class=\"productDetails__moreInfoLink vc-link vc-text-m\">sizing guide</button><!-- --></li><!-- --><!-- --><li _ngcontent-vc-app-c187=\"\">Location:<!-- -->Italy,\n          from\n          the seller Sepa<!-- --><!-- --></li><!-- --><li _ngcontent-vc-app-c187=\"\">Reference:<!-- --> 18896043</li></ul>"}, {"id": 19214311, "url": "https://fr.vestiairecollective.com//women-clothing/skirts/jean-paul-gaultier/black-denim-jeans-jean-paul-gaultier-skirt-19214311.shtml", "brand": "jean-paul-gaultier", "page_no": 0, "description": "<ul _ngcontent-vc-app-c187=\"\" class=\"descriptionList__block__list descriptionList__block__list--detail\"><li _ngcontent-vc-app-c187=\"\">Online since:<!-- --> 13/11/2021 </li><li _ngcontent-vc-app-c187=\"\">Categories : <!-- --> Women </li><li _ngcontent-vc-app-c187=\"\">Category:<!-- --> Clothing </li><li _ngcontent-vc-app-c187=\"\">Sub-category:<!-- --> Skirts </li><!-- --><li _ngcontent-vc-app-c187=\"\">Designer:<!-- --> Jean Paul Gaultier </li><!-- --><li _ngcontent-vc-app-c187=\"\"><span _ngcontent-vc-app-c187=\"\">Condition:<!-- --> Never worn, with tag</span><button _ngcontent-vc-app-c187=\"\" class=\"descriptionList__block__list__moreInfo vc-link vc-text-m\">More info</button></li><li _ngcontent-vc-app-c187=\"\">Material:<!-- --> Denim - Jeans <!-- --><!-- --><!-- --><!-- --></li><!-- --><!-- --><li _ngcontent-vc-app-c187=\"\">Color:<!-- --> Black </li><!-- --><!-- --><li _ngcontent-vc-app-c187=\"\">Size:<!-- --> 44 FR <button _ngcontent-vc-app-c187=\"\" class=\"productDetails__moreInfoLink vc-link vc-text-m\">sizing guide</button><!-- --></li><!-- --><li _ngcontent-vc-app-c187=\"\">Style:<!-- -->Vintage<!-- --></li><!-- --><li _ngcontent-vc-app-c187=\"\">Location:<!-- -->Portugal,\n          from\n          the seller Sara<!-- --><!-- --></li><!-- --><li _ngcontent-vc-app-c187=\"\">Reference:<!-- --> 19214311</li></ul>"}, {"id": 19003996, "url": "https://fr.vestiairecollective.com//women-clothing/knitwear/jean-paul-gaultier/other-wool-jean-paul-gaultier-knitwear-19003996.shtml", "brand": "jean-paul-gaultier", "page_no": 0, "description": "<ul _ngcontent-vc-app-c187=\"\" class=\"descriptionList__block__list descriptionList__block__list--detail\"><li _ngcontent-vc-app-c187=\"\">Online since:<!-- --> 03/11/2021 </li><li _ngcontent-vc-app-c187=\"\">Categories : <!-- --> Women </li><li _ngcontent-vc-app-c187=\"\">Category:<!-- --> Clothing </li><li _ngcontent-vc-app-c187=\"\">Sub-category:<!-- --> Knitwear </li><!-- --><li _ngcontent-vc-app-c187=\"\">Designer:<!-- --> Jean Paul Gaultier </li><!-- --><li _ngcontent-vc-app-c187=\"\"><span _ngcontent-vc-app-c187=\"\">Condition:<!-- --> Never worn</span><button _ngcontent-vc-app-c187=\"\" class=\"descriptionList__block__list__moreInfo vc-link vc-text-m\">More info</button></li><li _ngcontent-vc-app-c187=\"\">Material:<!-- --> Wool <!-- --><!-- --><!-- --><!-- --></li><!-- --><!-- --><li _ngcontent-vc-app-c187=\"\">Color:<!-- --> Other </li><!-- --><!-- --><li _ngcontent-vc-app-c187=\"\">Size:<!-- --> 42 FR <button _ngcontent-vc-app-c187=\"\" class=\"productDetails__moreInfoLink vc-link vc-text-m\">sizing guide</button><!-- --></li><!-- --><li _ngcontent-vc-app-c187=\"\">Style:<!-- -->Vintage<!-- --></li><!-- --><li _ngcontent-vc-app-c187=\"\">Location:<!-- -->Netherlands,\n          from\n          the seller Hans<!-- --><!-- --></li><!-- --><li _ngcontent-vc-app-c187=\"\">Reference:<!-- --> 19003996</li></ul>"}, {"id": 19217434, "url": "https://fr.vestiairecollective.com//women-clothing/tops/jean-paul-gaultier/white-cotton-jean-paul-gaultier-top-19217434.shtml", "brand": "jean-paul-gaultier", "page_no": 0, "description": "<ul _ngcontent-vc-app-c187=\"\" class=\"descriptionList__block__list descriptionList__block__list--detail\"><li _ngcontent-vc-app-c187=\"\">Online since:<!-- --> 13/11/2021 </li><li _ngcontent-vc-app-c187=\"\">Categories : <!-- --> Women </li><li _ngcontent-vc-app-c187=\"\">Category:<!-- --> Clothing </li><li _ngcontent-vc-app-c187=\"\">Sub-category:<!-- --> Tops </li><!-- --><li _ngcontent-vc-app-c187=\"\">Designer:<!-- --> Jean Paul Gaultier </li><!-- --><li _ngcontent-vc-app-c187=\"\"><span _ngcontent-vc-app-c187=\"\">Condition:<!-- --> Good condition</span><button _ngcontent-vc-app-c187=\"\" class=\"descriptionList__block__list__moreInfo vc-link vc-text-m\">More info</button></li><li _ngcontent-vc-app-c187=\"\">Material:<!-- --> Cotton <!-- --><!-- --><!-- --><!-- --></li><!-- --><!-- --><li _ngcontent-vc-app-c187=\"\">Color:<!-- --> White </li><!-- --><!-- --><li _ngcontent-vc-app-c187=\"\">Size:<!-- --> M International <button _ngcontent-vc-app-c187=\"\" class=\"productDetails__moreInfoLink vc-link vc-text-m\">sizing guide</button><!-- --></li><!-- --><li _ngcontent-vc-app-c187=\"\">Style:<!-- -->Vintage<!-- --></li><!-- --><li _ngcontent-vc-app-c187=\"\">Location:<!-- -->Germany,\n          from\n          the seller Mark<!-- --><!-- --></li><!-- --><li _ngcontent-vc-app-c187=\"\">Reference:<!-- --> 19217434</li></ul>"}, {"id": 18799462, "url": "https://fr.vestiairecollective.com//women-clothing/trousers/jean-paul-gaultier/multicolour-spandex-jean-paul-gaultier-trousers-18799462.shtml", "brand": "jean-paul-gaultier", "page_no": 0, "description": "<ul _ngcontent-vc-app-c187=\"\" class=\"descriptionList__block__list descriptionList__block__list--detail\"><li _ngcontent-vc-app-c187=\"\">Online since:<!-- --> 25/10/2021 </li><li _ngcontent-vc-app-c187=\"\">Categories : <!-- --> Women </li><li _ngcontent-vc-app-c187=\"\">Category:<!-- --> Clothing </li><li _ngcontent-vc-app-c187=\"\">Sub-category:<!-- --> Trousers </li><!-- --><li _ngcontent-vc-app-c187=\"\">Designer:<!-- --> Jean Paul Gaultier </li><!-- --><li _ngcontent-vc-app-c187=\"\"><span _ngcontent-vc-app-c187=\"\">Condition:<!-- --> Very good condition</span><button _ngcontent-vc-app-c187=\"\" class=\"descriptionList__block__list__moreInfo vc-link vc-text-m\">More info</button></li><li _ngcontent-vc-app-c187=\"\">Material:<!-- --> Spandex <!-- --><!-- --><!-- --><!-- --></li><!-- --><!-- --><li _ngcontent-vc-app-c187=\"\">Color:<!-- --> Multicolour </li><!-- --><!-- --><li _ngcontent-vc-app-c187=\"\">Size:<!-- --> 36 FR <button _ngcontent-vc-app-c187=\"\" class=\"productDetails__moreInfoLink vc-link vc-text-m\">sizing guide</button><!-- --></li><!-- --><!-- --><li _ngcontent-vc-app-c187=\"\">Location:<!-- -->France,\n          from\n          the seller ericka<!-- --><!-- --></li><!-- --><li _ngcontent-vc-app-c187=\"\">Reference:<!-- --> 18799462</li></ul>"}, {"id": 18789576, "url": "https://fr.vestiairecollective.com//women-clothing/dresses/jean-paul-gaultier/multicolour-polyester-jean-paul-gaultier-dress-18789576.shtml", "brand": "jean-paul-gaultier", "page_no": 0, "description": "<ul _ngcontent-vc-app-c187=\"\" class=\"descriptionList__block__list descriptionList__block__list--detail\"><li _ngcontent-vc-app-c187=\"\">Online since:<!-- --> 25/10/2021 </li><li _ngcontent-vc-app-c187=\"\">Categories : <!-- --> Women </li><li _ngcontent-vc-app-c187=\"\">Category:<!-- --> Clothing </li><li _ngcontent-vc-app-c187=\"\">Sub-category:<!-- --> Dresses </li><!-- --><li _ngcontent-vc-app-c187=\"\">Designer:<!-- --> Jean Paul Gaultier </li><!-- --><li _ngcontent-vc-app-c187=\"\"><span _ngcontent-vc-app-c187=\"\">Condition:<!-- --> Very good condition</span><button _ngcontent-vc-app-c187=\"\" class=\"descriptionList__block__list__moreInfo vc-link vc-text-m\">More info</button></li><li _ngcontent-vc-app-c187=\"\">Material:<!-- --> Polyester <!-- --><!-- --><!-- --><!-- --></li><!-- --><!-- --><li _ngcontent-vc-app-c187=\"\">Color:<!-- --> Multicolour </li><!-- --><!-- --><li _ngcontent-vc-app-c187=\"\">Size:<!-- --> 38 FR <button _ngcontent-vc-app-c187=\"\" class=\"productDetails__moreInfoLink vc-link vc-text-m\">sizing guide</button><!-- --></li><!-- --><!-- --><li _ngcontent-vc-app-c187=\"\">Location:<!-- -->France,\n          from\n          the seller karoline<!-- --><!-- --></li><!-- --><li _ngcontent-vc-app-c187=\"\">Reference:<!-- --> 18789576</li></ul>"}, {"id": 18804366, "url": "https://fr.vestiairecollective.com//women-clothing/dresses/jean-paul-gaultier/multicolour-synthetic-jean-paul-gaultier-dress-18804366.shtml", "brand": "jean-paul-gaultier", "page_no": 0, "description": "<ul _ngcontent-vc-app-c187=\"\" class=\"descriptionList__block__list descriptionList__block__list--detail\"><li _ngcontent-vc-app-c187=\"\">Online since:<!-- --> 25/10/2021 </li><li _ngcontent-vc-app-c187=\"\">Categories : <!-- --> Women </li><li _ngcontent-vc-app-c187=\"\">Category:<!-- --> Clothing </li><li _ngcontent-vc-app-c187=\"\">Sub-category:<!-- --> Dresses </li><!-- --><li _ngcontent-vc-app-c187=\"\">Designer:<!-- --> Jean Paul Gaultier </li><!-- --><li _ngcontent-vc-app-c187=\"\"><span _ngcontent-vc-app-c187=\"\">Condition:<!-- --> Very good condition</span><button _ngcontent-vc-app-c187=\"\" class=\"descriptionList__block__list__moreInfo vc-link vc-text-m\">More info</button></li><li _ngcontent-vc-app-c187=\"\">Material:<!-- --> Synthetic <!-- --><!-- --><!-- --><!-- --></li><!-- --><!-- --><li _ngcontent-vc-app-c187=\"\">Color:<!-- --> Multicolour </li><!-- --><!-- --><li _ngcontent-vc-app-c187=\"\">Size:<!-- --> M International <button _ngcontent-vc-app-c187=\"\" class=\"productDetails__moreInfoLink vc-link vc-text-m\">sizing guide</button><!-- --></li><!-- --><!-- --><li _ngcontent-vc-app-c187=\"\">Location:<!-- -->Italy,\n          from\n          the seller Sepa<!-- --><!-- --></li><!-- --><li _ngcontent-vc-app-c187=\"\">Reference:<!-- --> 18804366</li></ul>"}, {"id": 19111401, "url": "https://fr.vestiairecollective.com//men-clothing/t-shirts/jean-paul-gaultier/black-synthetic-jean-paul-gaultier-t-shirt-19111401.shtml", "brand": "jean-paul-gaultier", "page_no": 0, "description": "<ul _ngcontent-vc-app-c187=\"\" class=\"descriptionList__block__list descriptionList__block__list--detail\"><li _ngcontent-vc-app-c187=\"\">Online since:<!-- --> 08/11/2021 </li><li _ngcontent-vc-app-c187=\"\">Categories : <!-- --> Men </li><li _ngcontent-vc-app-c187=\"\">Category:<!-- --> Clothing </li><li _ngcontent-vc-app-c187=\"\">Sub-category:<!-- --> T-shirts </li><!-- --><li _ngcontent-vc-app-c187=\"\">Designer:<!-- --> Jean Paul Gaultier </li><!-- --><li _ngcontent-vc-app-c187=\"\"><span _ngcontent-vc-app-c187=\"\">Condition:<!-- --> Very good condition</span><button _ngcontent-vc-app-c187=\"\" class=\"descriptionList__block__list__moreInfo vc-link vc-text-m\">More info</button></li><li _ngcontent-vc-app-c187=\"\">Material:<!-- --> Synthetic <!-- --><!-- --><!-- --><!-- --></li><!-- --><!-- --><li _ngcontent-vc-app-c187=\"\">Color:<!-- --> Black </li><!-- --><!-- --><li _ngcontent-vc-app-c187=\"\">Size:<!-- --> M International <button _ngcontent-vc-app-c187=\"\" class=\"productDetails__moreInfoLink vc-link vc-text-m\">sizing guide</button><!-- --></li><!-- --><!-- --><li _ngcontent-vc-app-c187=\"\">Location:<!-- -->France,\n          from\n          the seller Julian<!-- --><!-- --></li><!-- --><li _ngcontent-vc-app-c187=\"\">Reference:<!-- --> 19111401</li></ul>"}, {"id": 19157591, "url": "https://fr.vestiairecollective.com//women-accessories/sunglasses/jean-paul-gaultier/silver-metal-jean-paul-gaultier-sunglasses-19157591.shtml", "brand": "jean-paul-gaultier", "page_no": 0, "description": "<ul _ngcontent-vc-app-c187=\"\" class=\"descriptionList__block__list descriptionList__block__list--detail\"><li _ngcontent-vc-app-c187=\"\">Online since:<!-- --> 11/11/2021 </li><li _ngcontent-vc-app-c187=\"\">Categories : <!-- --> Women </li><li _ngcontent-vc-app-c187=\"\">Category:<!-- --> Accessories </li><li _ngcontent-vc-app-c187=\"\">Sub-category:<!-- --> Sunglasses </li><!-- --><li _ngcontent-vc-app-c187=\"\">Designer:<!-- --> Jean Paul Gaultier </li><!-- --><li _ngcontent-vc-app-c187=\"\"><span _ngcontent-vc-app-c187=\"\">Condition:<!-- --> Very good condition</span><button _ngcontent-vc-app-c187=\"\" class=\"descriptionList__block__list__moreInfo vc-link vc-text-m\">More info</button></li><li _ngcontent-vc-app-c187=\"\">Material:<!-- --> Metal <!-- --><!-- --><!-- --><!-- --></li><!-- --><!-- --><li _ngcontent-vc-app-c187=\"\">Color:<!-- --> Silver </li><!-- --><!-- --><!-- --><li _ngcontent-vc-app-c187=\"\">Style:<!-- -->Vintage<!-- --></li><!-- --><li _ngcontent-vc-app-c187=\"\">Location:<!-- -->Italy,\n          from\n          the seller ophertyciocci<!-- --><!-- --></li><!-- --><li _ngcontent-vc-app-c187=\"\">Reference:<!-- --> 19157591</li></ul>"}, {"id": 19175460, "url": "https://fr.vestiairecollective.com//men-clothing/t-shirts/jean-paul-gaultier/multicolour-polyester-jean-paul-gaultier-t-shirt-19175460.shtml", "brand": "jean-paul-gaultier", "page_no": 0, "description": "<ul _ngcontent-vc-app-c187=\"\" class=\"descriptionList__block__list descriptionList__block__list--detail\"><li _ngcontent-vc-app-c187=\"\">Online since:<!-- --> 11/11/2021 </li><li _ngcontent-vc-app-c187=\"\">Categories : <!-- --> Men </li><li _ngcontent-vc-app-c187=\"\">Category:<!-- --> Clothing </li><li _ngcontent-vc-app-c187=\"\">Sub-category:<!-- --> T-shirts </li><!-- --><li _ngcontent-vc-app-c187=\"\">Designer:<!-- --> Jean Paul Gaultier </li><!-- --><li _ngcontent-vc-app-c187=\"\"><span _ngcontent-vc-app-c187=\"\">Condition:<!-- --> Never worn</span><button _ngcontent-vc-app-c187=\"\" class=\"descriptionList__block__list__moreInfo vc-link vc-text-m\">More info</button></li><li _ngcontent-vc-app-c187=\"\">Material:<!-- --> Polyester <!-- --><!-- --><!-- --><!-- --></li><!-- --><!-- --><li _ngcontent-vc-app-c187=\"\">Color:<!-- --> Multicolour </li><!-- --><!-- --><li _ngcontent-vc-app-c187=\"\">Size:<!-- --> M International <button _ngcontent-vc-app-c187=\"\" class=\"productDetails__moreInfoLink vc-link vc-text-m\">sizing guide</button><!-- --></li><!-- --><!-- --><li _ngcontent-vc-app-c187=\"\">Location:<!-- -->United Kingdom,\n          from\n          the seller Felix<!-- --><!-- --></li><!-- --><li _ngcontent-vc-app-c187=\"\">Reference:<!-- --> 19175460</li></ul>"}, {"id": 18845214, "url": "https://fr.vestiairecollective.com//men-clothing/jackets/jean-paul-gaultier/black-cotton-jean-paul-gaultier-jacket-18845214.shtml", "brand": "jean-paul-gaultier", "page_no": 0, "description": "<ul _ngcontent-vc-app-c187=\"\" class=\"descriptionList__block__list descriptionList__block__list--detail\"><li _ngcontent-vc-app-c187=\"\">Online since:<!-- --> 27/10/2021 </li><li _ngcontent-vc-app-c187=\"\">Categories : <!-- --> Men </li><li _ngcontent-vc-app-c187=\"\">Category:<!-- --> Clothing </li><li _ngcontent-vc-app-c187=\"\">Sub-category:<!-- --> Jackets  </li><!-- --><li _ngcontent-vc-app-c187=\"\">Designer:<!-- --> Jean Paul Gaultier </li><!-- --><li _ngcontent-vc-app-c187=\"\"><span _ngcontent-vc-app-c187=\"\">Condition:<!-- --> Very good condition</span><button _ngcontent-vc-app-c187=\"\" class=\"descriptionList__block__list__moreInfo vc-link vc-text-m\">More info</button></li><li _ngcontent-vc-app-c187=\"\">Material:<!-- --> Cotton <!-- --><!-- --><!-- --><!-- --></li><!-- --><!-- --><li _ngcontent-vc-app-c187=\"\">Color:<!-- --> Black </li><!-- --><!-- --><li _ngcontent-vc-app-c187=\"\">Size:<!-- --> 48 IT <button _ngcontent-vc-app-c187=\"\" class=\"productDetails__moreInfoLink vc-link vc-text-m\">sizing guide</button><!-- --></li><!-- --><!-- --><li _ngcontent-vc-app-c187=\"\">Location:<!-- -->France,\n          from\n          the seller Varvara<!-- --><!-- --></li><!-- --><li _ngcontent-vc-app-c187=\"\">Reference:<!-- --> 18845214</li></ul>"}, {"id": 19173730, "url": "https://fr.vestiairecollective.com//women-clothing/trousers/jean-paul-gaultier/blue-cotton-jean-paul-gaultier-trousers-19173730.shtml", "brand": "jean-paul-gaultier", "page_no": 0, "description": "<ul _ngcontent-vc-app-c187=\"\" class=\"descriptionList__block__list descriptionList__block__list--detail\"><li _ngcontent-vc-app-c187=\"\">Online since:<!-- --> 11/11/2021 </li><li _ngcontent-vc-app-c187=\"\">Categories : <!-- --> Women </li><li _ngcontent-vc-app-c187=\"\">Category:<!-- --> Clothing </li><li _ngcontent-vc-app-c187=\"\">Sub-category:<!-- --> Trousers </li><!-- --><li _ngcontent-vc-app-c187=\"\">Designer:<!-- --> Jean Paul Gaultier </li><!-- --><li _ngcontent-vc-app-c187=\"\"><span _ngcontent-vc-app-c187=\"\">Condition:<!-- --> Very good condition</span><button _ngcontent-vc-app-c187=\"\" class=\"descriptionList__block__list__moreInfo vc-link vc-text-m\">More info</button></li><li _ngcontent-vc-app-c187=\"\">Material:<!-- --> Cotton <!-- --><!-- --><!-- --><!-- --></li><!-- --><!-- --><li _ngcontent-vc-app-c187=\"\">Color:<!-- --> Blue </li><!-- --><!-- --><li _ngcontent-vc-app-c187=\"\">Size:<!-- --> 40 FR <button _ngcontent-vc-app-c187=\"\" class=\"productDetails__moreInfoLink vc-link vc-text-m\">sizing guide</button><!-- --></li><!-- --><!-- --><li _ngcontent-vc-app-c187=\"\">Location:<!-- -->France,\n          from\n          the seller isabelle<!-- --><!-- --></li><!-- --><li _ngcontent-vc-app-c187=\"\">Reference:<!-- --> 19173730</li></ul>"}, {"id": 19094482, "url": "https://fr.vestiairecollective.com//men-bags/small-bags-wallets-cases/jean-paul-gaultier/navy-synthetic-jean-paul-gaultier-small-bag-19094482.shtml", "brand": "jean-paul-gaultier", "page_no": 0, "description": "<ul _ngcontent-vc-app-c187=\"\" class=\"descriptionList__block__list descriptionList__block__list--detail\"><li _ngcontent-vc-app-c187=\"\">Online since:<!-- --> 08/11/2021 </li><li _ngcontent-vc-app-c187=\"\">Categories : <!-- --> Men </li><li _ngcontent-vc-app-c187=\"\">Category:<!-- --> Bags </li><li _ngcontent-vc-app-c187=\"\">Sub-category:<!-- --> Small bags, wallets &amp; cases </li><!-- --><li _ngcontent-vc-app-c187=\"\">Designer:<!-- --> Jean Paul Gaultier </li><!-- --><li _ngcontent-vc-app-c187=\"\"><span _ngcontent-vc-app-c187=\"\">Condition:<!-- --> Never worn</span><button _ngcontent-vc-app-c187=\"\" class=\"descriptionList__block__list__moreInfo vc-link vc-text-m\">More info</button></li><li _ngcontent-vc-app-c187=\"\">Material:<!-- --> Synthetic <!-- --><!-- --><!-- --><!-- --></li><!-- --><!-- --><li _ngcontent-vc-app-c187=\"\">Color:<!-- --> Navy </li><!-- --><!-- --><!-- --><!-- --><li _ngcontent-vc-app-c187=\"\">Location:<!-- -->Portugal,\n          from\n          the seller Isabelle<!-- --><!-- --></li><!-- --><li _ngcontent-vc-app-c187=\"\">Reference:<!-- --> 19094482</li></ul>"}, {"id": 18824078, "url": "https://fr.vestiairecollective.com//women-clothing/dresses/jean-paul-gaultier/multicolour-viscose-jean-paul-gaultier-dress-18824078.shtml", "brand": "jean-paul-gaultier", "page_no": 0, "description": "<ul _ngcontent-vc-app-c187=\"\" class=\"descriptionList__block__list descriptionList__block__list--detail\"><li _ngcontent-vc-app-c187=\"\">Online since:<!-- --> 26/10/2021 </li><li _ngcontent-vc-app-c187=\"\">Categories : <!-- --> Women </li><li _ngcontent-vc-app-c187=\"\">Category:<!-- --> Clothing </li><li _ngcontent-vc-app-c187=\"\">Sub-category:<!-- --> Dresses </li><!-- --><li _ngcontent-vc-app-c187=\"\">Designer:<!-- --> Jean Paul Gaultier </li><!-- --><li _ngcontent-vc-app-c187=\"\"><span _ngcontent-vc-app-c187=\"\">Condition:<!-- --> Very good condition</span><button _ngcontent-vc-app-c187=\"\" class=\"descriptionList__block__list__moreInfo vc-link vc-text-m\">More info</button></li><li _ngcontent-vc-app-c187=\"\">Material:<!-- --> Viscose <!-- --><!-- --><!-- --><!-- --></li><!-- --><!-- --><li _ngcontent-vc-app-c187=\"\">Color:<!-- --> Multicolour </li><!-- --><!-- --><li _ngcontent-vc-app-c187=\"\">Size:<!-- --> M International <button _ngcontent-vc-app-c187=\"\" class=\"productDetails__moreInfoLink vc-link vc-text-m\">sizing guide</button><!-- --></li><!-- --><!-- --><li _ngcontent-vc-app-c187=\"\">Location:<!-- -->Italy,\n          from\n          the seller Sepa<!-- --><!-- --></li><!-- --><li _ngcontent-vc-app-c187=\"\">Reference:<!-- --> 18824078</li></ul>"}, {"id": 19143326, "url": "https://fr.vestiairecollective.com//women-clothing/skirts/jean-paul-gaultier/multicolour-wool-jean-paul-gaultier-skirt-19143326.shtml", "brand": "jean-paul-gaultier", "page_no": 0, "description": "<ul _ngcontent-vc-app-c187=\"\" class=\"descriptionList__block__list descriptionList__block__list--detail\"><li _ngcontent-vc-app-c187=\"\">Online since:<!-- --> 10/11/2021 </li><li _ngcontent-vc-app-c187=\"\">Categories : <!-- --> Women </li><li _ngcontent-vc-app-c187=\"\">Category:<!-- --> Clothing </li><li _ngcontent-vc-app-c187=\"\">Sub-category:<!-- --> Skirts </li><!-- --><li _ngcontent-vc-app-c187=\"\">Designer:<!-- --> Jean Paul Gaultier </li><!-- --><li _ngcontent-vc-app-c187=\"\"><span _ngcontent-vc-app-c187=\"\">Condition:<!-- --> Fair condition</span><button _ngcontent-vc-app-c187=\"\" class=\"descriptionList__block__list__moreInfo vc-link vc-text-m\">More info</button></li><li _ngcontent-vc-app-c187=\"\">Material:<!-- --> Wool <!-- --><!-- --><!-- --><!-- --></li><!-- --><!-- --><li _ngcontent-vc-app-c187=\"\">Color:<!-- --> Multicolour </li><!-- --><!-- --><li _ngcontent-vc-app-c187=\"\">Size:<!-- --> M International <button _ngcontent-vc-app-c187=\"\" class=\"productDetails__moreInfoLink vc-link vc-text-m\">sizing guide</button><!-- --></li><!-- --><li _ngcontent-vc-app-c187=\"\">Style:<!-- -->Vintage<!-- --></li><!-- --><li _ngcontent-vc-app-c187=\"\">Location:<!-- -->France,\n          from\n          the seller solange<!-- --><!-- --></li><!-- --><li _ngcontent-vc-app-c187=\"\">Reference:<!-- --> 19143326</li></ul>"}, {"id": 19076463, "url": "https://fr.vestiairecollective.com//women-clothing/dresses/jean-paul-gaultier/black-polyester-jean-paul-gaultier-dress-19076463.shtml", "brand": "jean-paul-gaultier", "page_no": 0, "description": "<ul _ngcontent-vc-app-c187=\"\" class=\"descriptionList__block__list descriptionList__block__list--detail\"><li _ngcontent-vc-app-c187=\"\">Online since:<!-- --> 07/11/2021 </li><li _ngcontent-vc-app-c187=\"\">Categories : <!-- --> Women </li><li _ngcontent-vc-app-c187=\"\">Category:<!-- --> Clothing </li><li _ngcontent-vc-app-c187=\"\">Sub-category:<!-- --> Dresses </li><!-- --><li _ngcontent-vc-app-c187=\"\">Designer:<!-- --> Jean Paul Gaultier </li><!-- --><li _ngcontent-vc-app-c187=\"\"><span _ngcontent-vc-app-c187=\"\">Condition:<!-- --> Good condition</span><button _ngcontent-vc-app-c187=\"\" class=\"descriptionList__block__list__moreInfo vc-link vc-text-m\">More info</button></li><li _ngcontent-vc-app-c187=\"\">Material:<!-- --> Polyester <!-- --><!-- --><!-- --><!-- --></li><!-- --><!-- --><li _ngcontent-vc-app-c187=\"\">Color:<!-- --> Black </li><!-- --><!-- --><li _ngcontent-vc-app-c187=\"\">Size:<!-- --> 44 IT <button _ngcontent-vc-app-c187=\"\" class=\"productDetails__moreInfoLink vc-link vc-text-m\">sizing guide</button><!-- --></li><!-- --><!-- --><li _ngcontent-vc-app-c187=\"\">Location:<!-- -->Italy,\n          from\n          the seller Laura<!-- --><!-- --></li><!-- --><li _ngcontent-vc-app-c187=\"\">Reference:<!-- --> 19076463</li></ul>"}, {"id": 18733789, "url": "https://fr.vestiairecollective.com//women-clothing/skirts/jean-paul-gaultier/blue-denim-jeans-jean-paul-gaultier-skirt-18733789.shtml", "brand": "jean-paul-gaultier", "page_no": 0, "description": "<ul _ngcontent-vc-app-c187=\"\" class=\"descriptionList__block__list descriptionList__block__list--detail\"><li _ngcontent-vc-app-c187=\"\">Online since:<!-- --> 22/10/2021 </li><li _ngcontent-vc-app-c187=\"\">Categories : <!-- --> Women </li><li _ngcontent-vc-app-c187=\"\">Category:<!-- --> Clothing </li><li _ngcontent-vc-app-c187=\"\">Sub-category:<!-- --> Skirts </li><!-- --><li _ngcontent-vc-app-c187=\"\">Designer:<!-- --> Jean Paul Gaultier </li><!-- --><li _ngcontent-vc-app-c187=\"\"><span _ngcontent-vc-app-c187=\"\">Condition:<!-- --> Never worn</span><button _ngcontent-vc-app-c187=\"\" class=\"descriptionList__block__list__moreInfo vc-link vc-text-m\">More info</button></li><li _ngcontent-vc-app-c187=\"\">Material:<!-- --> Denim - Jeans <!-- --><!-- --><!-- --><!-- --></li><!-- --><!-- --><li _ngcontent-vc-app-c187=\"\">Color:<!-- --> Blue </li><!-- --><!-- --><li _ngcontent-vc-app-c187=\"\">Size:<!-- --> 40 FR <button _ngcontent-vc-app-c187=\"\" class=\"productDetails__moreInfoLink vc-link vc-text-m\">sizing guide</button><!-- --></li><!-- --><!-- --><li _ngcontent-vc-app-c187=\"\">Location:<!-- -->Spain,\n          from\n          the seller RUBEN<!-- --><!-- --></li><!-- --><li _ngcontent-vc-app-c187=\"\">Reference:<!-- --> 18733789</li></ul>"}]